biteasy/__init__.py
biteasy/_biteasy.py
biteasy-0.1.0.dist-info/METADATA
biteasy-0.1.0.dist-info/WHEEL
biteasy-0.1.0.dist-info/licenses/LICENSE
biteasy-0.1.0.dist-info/RECORD
